stop_the_vcr/__init__.py
stop_the_vcr/matchers.py
stop_the_vcr-0.1.5.dist-info/METADATA
stop_the_vcr-0.1.5.dist-info/WHEEL
stop_the_vcr-0.1.5.dist-info/RECORD
